{
    "title": "谁认识Slender MAN",
    "author": "4072",
    "replyCount": 17,
    "timestamp": 1367746800,
    "txt_content": "   坛子有位仁兄，就是这位\n朋友，见了此帖回个话，我找你有事{:10_505:}\n\n\n\n\n\n这帖没发继续了",
    "replies": [
        {
            "author": "Evan丶桑",
            "timestamp": 1367746860,
            "txt_content": "认识的人都死了~"
        },
        {
            "author": "听、风语",
            "timestamp": 1367746860,
            "txt_content": "这是谁？没五官捏……"
        },
        {
            "author": "NB人士",
            "timestamp": 1367746920,
            "txt_content": "这个\n我知道他\n但是不认识他。。。"
        },
        {
            "author": "4072",
            "timestamp": 1367746920,
            "txt_content": "听、风语 发表于 2013-5-5 17:41 \n这是谁？没五官捏……\nSlender MAN"
        },
        {
            "author": "4072",
            "timestamp": 1367746980,
            "txt_content": "Evan丶桑 发表于 2013-5-5 17:41 \n认识的人都死了~\n我是他亲戚"
        },
        {
            "author": "板栗。酱",
            "timestamp": 1367746980,
            "txt_content": "我~~不认识。。。"
        },
        {
            "author": "azsx6912121",
            "timestamp": 1367746980,
            "txt_content": "你说我么··············LZ········我叫··········Slender MAN，叫我MAN就行，别叫真名···········"
        },
        {
            "author": "4072",
            "timestamp": 1367747040,
            "txt_content": "板栗。酱 发表于 2013-5-5 17:43 \n我~~不认识。。。\n真的吗{:10_512:}"
        },
        {
            "author": "板栗。酱",
            "timestamp": 1367747100,
            "txt_content": "4072 发表于 2013-5-5 17:44 \n真的吗\n我认识~\n在8楼~"
        },
        {
            "author": "4072",
            "timestamp": 1367747100,
            "txt_content": "azsx6912121 发表于 2013-5-5 17:43 \n你说我么··············LZ········我叫··········Slender MAN，叫我MAN就 ...\n你终于来了，我等了你5年，你杀光了镇子里所有的人"
        },
        {
            "author": "Evan丶桑",
            "timestamp": 1367747160,
            "txt_content": "4072 发表于 2013-5-5 17:43 \n我是他亲戚\n我表示《瘦长鬼影 降临》还没通关~"
        },
        {
            "author": "a982617537",
            "timestamp": 1367747460,
            "txt_content": "认识的人都死了+差点看成spiderman。"
        },
        {
            "author": "天界杀手",
            "timestamp": 1367747460,
            "txt_content": "4072 发表于 2013-5-5 17:43 \n我是他亲戚\n我知道，你去右上角的本版（改为用户）搜索Slender MAN，如果是你发的头像是呢个人的头像就是他啦"
        },
        {
            "author": "azsx6912121",
            "timestamp": 1367747640,
            "txt_content": "4072 发表于 2013-5-5 17:45 \n你终于来了，我等了你5年，你杀光了镇子里所有的人\n嘿···········兄·············弟·········"
        },
        {
            "author": "4072",
            "timestamp": 1367749500,
            "txt_content": "azsx6912121 发表于 2013-5-5 17:54 \n嘿···········兄·············弟·········\n这是你么"
        },
        {
            "author": "azsx6912121",
            "timestamp": 1367749680,
            "txt_content": "4072 发表于 2013-5-5 18:25 \n这是你么\n图挂了·····"
        },
        {
            "author": "4072",
            "timestamp": 1367749800,
            "txt_content": "azsx6912121 发表于 2013-5-5 18:28 \n图挂了·····\nNO，哦不\n"
        }
    ]
}