{
    "title": "CK的第一个文章",
    "author": "850624773",
    "replyCount": 3,
    "timestamp": 1373389740,
    "txt_content": "  2036年9月……\n  一个男孩在苦恼着。“秦新，在干什么呢？”突然远处跑来一个女孩问道。“我在想怎么回去啊！对了，秋，你知不知道怎么回去呢？”那个叫秦新的男孩说到。女孩看了看秦新叹了口气：“谁知道，你怎么还在想这事？”\n\n\n“喂喂，秦新。你有没有玩过《我的世界》？”“没有啊。”秦新转过来，回答了那个同学的问题。“唉啊！你奥特了！你去上网找找：我的世界 beta版。现在我们班上好多人在玩呢！”“哦，是\n\n么？”秦新回答道。\n\n  上课时，老师讲的话，他一句都没听进去。一放学，老师刚刚说：“好了，这节课上到这里……”只听“搜————”的一声。“挖槽！秦新你跑那么快干什么！”\n\n  一回到家，秦新马上打开电脑，搜索。“！！！哇！这么好！有血量，有怪物，要自己生存下去……”他暗暗想到，又看了几个视频，合成表……\n\n  正当他看的高兴的时候……QQ上发来了信息：“秦新，在么？《我的世界》还可以吧。”他一看。哦，原来是上回的那个同学。（就是推荐他玩我的世界那个）“是啊，看了。没想到真不错啊！”\n\n“嘿嘿~不错吧。告诉你，他只是只有一个人设计的！”  “undefined 纳尼！”秦新发了个惊讶的表情。“嘿嘿，我这有个中文的，你去玩吧~”说完，他把一个压缩文档发了过来。就下了线。后面的事，\n\n不用我说你们也知道……\n\n\n  刚刚从回想中回过神来，就回了一句嘴， “啊啊啊，我知道了，真是的。”秦新不满的瞪了秋一眼。“对了，如果我没记错的话，晚上是会有…………………………没错吧”“没有错，是会有那个”\n\n秋看了秦新一眼说。“啊!”秦新跳起来，“那我们去看看有没有什么可以住的地方吧……”这可不像我的世界一样可以挖泥土建房子啊…………秦新想到。这毕竟还是一个真实的世界啊。哎呀……\n\n  “秦新，快来！”正在他胡思乱想的时候，一阵声音打断了他的思路。“恩”秦新站起来，往声音发出的地方走去。",
    "replies": [
        {
            "author": "南条寺夢路",
            "timestamp": 1373389980,
            "txt_content": "看不见 - -         "
        },
        {
            "author": "xialingjing",
            "timestamp": 1373390100,
            "txt_content": "早就告诉你不要过度灌水，不听。。封了吧。。"
        },
        {
            "author": "lichi2050",
            "timestamp": 1373393640,
            "txt_content": "看不见啊，LZ被禁言了?"
        }
    ]
}