{
    "title": "【The Terminator 2 】终结者——阿诺",
    "author": "甘乐丶",
    "replyCount": 16,
    "timestamp": 1390781940,
    "txt_content": " 本帖最后由 甘乐丶 于 2014-2-2 11:27 编辑 \n\n大家好~我甘乐丶{:10_492:}又来分享皮肤啦~\n这是我第二次发皮肤分享,有意见的尽管吐槽啦~\n您的意见对我来说很重要~{:10_510:}\n\n下载地址在上面啦~{:10_523:}\n\n\n\n\n\n\n下载 (1).png\n(18.86 KB, 下载次数: 18)\n\n\n\n\n下载附件\n\n\n2014-1-27 08:17 上传\n\n\n\n\n\n\n\n\n终结者\n\n\n\n\n\n\n\n\n\n\n\n下载.png\n(18.6 KB, 下载次数: 21)\n\n\n\n\n下载附件\n\n\n2014-1-27 08:17 上传\n\n\n\n\n\n\n\n\n终结者 0.0\n\n\n\n\n\n\n\n\n\n\n\n2f738bd4b31c8701735fbced267f9e2f060828381e30dfec.jpg\n(224.28 KB, 下载次数: 18)\n\n\n\n\n下载附件\n\n\n2014-1-27 08:21 上传\n\n\n\n\n\n\n\n\n和真人比起来。。。充满了自卑感\n\n\n\n\n\n\n",
    "replies": [
        {
            "author": "953142925",
            "timestamp": 1390782240,
            "txt_content": "路过打酱油，顶个\n沙发，舒服ing！"
        },
        {
            "author": "Milk_",
            "timestamp": 1390782360,
            "txt_content": "板凳...            "
        },
        {
            "author": "NekomancerLeko",
            "timestamp": 1390784400,
            "txt_content": "果断顶=-=这个好"
        },
        {
            "author": "TZZS.G",
            "timestamp": 1390784760,
            "txt_content": "真人是白皮肤啊{:10_493:}"
        },
        {
            "author": "147380124",
            "timestamp": 1390790400,
            "txt_content": "是不是有了这个皮肤就打不死啊？顶一个！"
        },
        {
            "author": "zdyxiaokeai",
            "timestamp": 1390791240,
            "txt_content": "147380124 发表于 2014-1-27 10:40\n是不是有了这个皮肤就打不死啊？顶一个！\n我记得终结者2的结局...T600跳岩浆(铁水)还是死了\n皮肤白不白倒还好,终结者1和2里都是涂了古铜色晒肌肉出场的"
        },
        {
            "author": "464982331",
            "timestamp": 1390792380,
            "txt_content": "经典！！！"
        },
        {
            "author": "a129487039",
            "timestamp": 1390792680,
            "txt_content": "不错不错~~"
        },
        {
            "author": "a129487039",
            "timestamp": 1390793220,
            "txt_content": "不错不错   "
        },
        {
            "author": "逗比762",
            "timestamp": 1390798500,
            "txt_content": "墨镜看起来怪怪的。。。"
        },
        {
            "author": "甘乐丶",
            "timestamp": 1390832820,
            "txt_content": "TZZS.G 发表于 2014-1-27 09:06\n真人是白皮肤啊\n{:10_497:}          黑一点比较有汉子的味道吧"
        },
        {
            "author": "MC猪人",
            "timestamp": 1404038640,
            "txt_content": "不错的皮肤\n\n\n\n\n\n\n\n\n\n\n\n\n\n"
        },
        {
            "author": "甘乐丶",
            "timestamp": 1404198480,
            "txt_content": "MC猪人 发表于 2014-6-29 18:44\n**** 作者被禁止或删除 内容自动屏蔽 ****\n谢谢支持{:10_512:}"
        },
        {
            "author": "小蛋蛋QAQ",
            "timestamp": 1404563820,
            "txt_content": "我说能不能做终结者，机器的"
        },
        {
            "author": "甘乐丶",
            "timestamp": 1404630900,
            "txt_content": "小蛋蛋QAQ 发表于 2014-7-5 20:37\n我说能不能做终结者，机器的\n终极机器人? 是\"骨架\"终结者吗{:10_492:}"
        },
        {
            "author": "小蛋蛋QAQ",
            "timestamp": 1404639960,
            "txt_content": "甘乐丶 发表于 2014-7-6 15:15\n终极机器人? 是\"骨架\"终结者吗\n没错阿，能做不- -"
        }
    ]
}