{
    "title": "服务器要加HIM插件吗。。",
    "author": "Faint",
    "replyCount": 19,
    "timestamp": 1404711060,
    "txt_content": "如题{:10_513:}\nHIM插件就是那个掉玩家头的，还会生成祭坛的那东西、、、{:10_517:}",
    "replies": [
        {
            "author": "lisongnan7",
            "timestamp": 1404711240,
            "txt_content": "看个人爱好了"
        },
        {
            "author": "52Dora",
            "timestamp": 1404711300,
            "txt_content": "服务器内部的话题能不要发到MCBBS吗？"
        },
        {
            "author": "Aikawastep",
            "timestamp": 1404711480,
            "txt_content": "你这么水真的没关系?"
        },
        {
            "author": "leavessoft",
            "timestamp": 1404711600,
            "txt_content": "不建议加。。。"
        },
        {
            "author": "MC大湿",
            "timestamp": 1404711660,
            "txt_content": "\n\nhim插件太丧心病狂了 不推荐加him插件"
        },
        {
            "author": "我叫龙浩晨",
            "timestamp": 1404712320,
            "txt_content": "······him···插件    算了吧"
        },
        {
            "author": "784746813",
            "timestamp": 1404712500,
            "txt_content": "Aikawastep 发表于 2014-7-7 13:38\n你这么水真的没关系?\n小水怡情，大水伤身"
        },
        {
            "author": "Aikawastep",
            "timestamp": 1404712620,
            "txt_content": "784746813 发表于 2014-7-7 13:55\n小水怡情，大水伤身\n神烦狗OAO..."
        },
        {
            "author": "784746813",
            "timestamp": 1404713400,
            "txt_content": "Aikawastep 发表于 2014-7-7 13:57\n神烦狗OAO...\n对呀，我就是很烦~"
        },
        {
            "author": "Aikawastep",
            "timestamp": 1404713460,
            "txt_content": "784746813 发表于 2014-7-7 14:10\n对呀，我就是很烦~\n← ←这节奏..."
        },
        {
            "author": "784746813",
            "timestamp": 1404713520,
            "txt_content": "Aikawastep 发表于 2014-7-7 14:11\n← ←这节奏...\n腐竹~你好~我是曲奇饼"
        },
        {
            "author": "z3120086",
            "timestamp": 1404713580,
            "txt_content": "简直丧心病狂，你服务器里的人绝对会反对的"
        },
        {
            "author": "恶小魂",
            "timestamp": 1404713580,
            "txt_content": "你喜欢HIM吗？"
        },
        {
            "author": "Aikawastep",
            "timestamp": 1404713700,
            "txt_content": "784746813 发表于 2014-7-7 14:12\n腐竹~你好~我是曲奇饼\nOAO，其实我还是不认识..."
        },
        {
            "author": "784746813",
            "timestamp": 1404713940,
            "txt_content": "Aikawastep 发表于 2014-7-7 14:15\nOAO，其实我还是不认识...\n那是很久以前了~"
        },
        {
            "author": "1481772656",
            "timestamp": 1404714480,
            "txt_content": "额，这个插件最好别加，但加也行"
        },
        {
            "author": "thyze",
            "timestamp": 1404716760,
            "txt_content": "如果你不怕你们玩家的屋子被HIM拆了的话。。\n随便{:10_532:}"
        },
        {
            "author": "1.3806",
            "timestamp": 1404717660,
            "txt_content": "好东西啊"
        },
        {
            "author": "きのこMogu_",
            "timestamp": 1404717780,
            "txt_content": "{:10_495:}你可以加但是你的玩家会行云流水"
        }
    ]
}