{
    "title": "熊孩子",
    "author": "Suzimo",
    "replyCount": 15,
    "timestamp": 1409196900,
    "txt_content": "新进服务器的玩家 就有3组绿宝石 好几组钻石  这是几个意思？我的世界难道有挂？ 求解 本人就是op 没有OP给他刷",
    "replies": [
        {
            "author": "亿豪",
            "timestamp": 1409196960,
            "txt_content": "你设置的物品吧"
        },
        {
            "author": "亿豪",
            "timestamp": 1409197020,
            "txt_content": "就像新进去的玩家手中总有一套工具。镐子等等"
        },
        {
            "author": "ZGA",
            "timestamp": 1409197140,
            "txt_content": "是有一些挂\n但是要安装的\n            ——你说，我是新手么？"
        },
        {
            "author": "ZGA",
            "timestamp": 1409197200,
            "txt_content": "亿豪 发表于 2014-8-28 11:37\n就像新进去的玩家手中总有一套工具。镐子等等\n那个是石质的 上面是绿宝石 钻石 不一样\n            ——你说，我是新手么？"
        },
        {
            "author": "eaaaaa",
            "timestamp": 1409197260,
            "txt_content": "NEI或者TMI内置修改，或者设置的第一次进去服务器得到的物品"
        },
        {
            "author": "niop",
            "timestamp": 1409197260,
            "txt_content": "ZGA 发表于 2014-8-28 11:39\n是有一些挂\n但是要安装的\n            ——你说，我是新手么？\n{:10_532:}你{:10_532:}就{:10_532:}是{:10_532:}新{:10_532:}手{:10_532:}"
        },
        {
            "author": "eaaaaa",
            "timestamp": 1409197320,
            "txt_content": "ZGA 发表于 2014-8-28 11:40\n那个是石质的 上面是绿宝石 钻石 不一样\n            ——你说，我是新手么？ ...\n回复 小尾巴  我不知道你是不是新手"
        },
        {
            "author": "ZGA",
            "timestamp": 1409197380,
            "txt_content": "eaaaaa 发表于 2014-8-28 11:41\nNEI或者TMI内置修改，或者设置的第一次进去服务器得到的物品\nNEI TMI在服务器里如果没有权限 是不可能用的\n            ——你说，我是新手么？"
        },
        {
            "author": "ZGA",
            "timestamp": 1409197380,
            "txt_content": "eaaaaa 发表于 2014-8-28 11:42\n回复 小尾巴  我不知道你是不是新手\n那个不是小尾巴→_→\n还有你见过三天四级的新手么？\n            ——你说，我是新手么？"
        },
        {
            "author": "Lungrisser",
            "timestamp": 1409197440,
            "txt_content": "ZGA 发表于 2014-8-28 11:43\nNEI TMI在服务器里如果没有权限 是不可能用的\n            ——你说，我是新手么？ ...\n不像新手啊"
        },
        {
            "author": "ZGA",
            "timestamp": 1409197500,
            "txt_content": "Lungrisser 发表于 2014-8-28 11:44\n不像新手啊\n对啊对啊 某人还一直说我是新手→_→ @niop"
        },
        {
            "author": "qxdnfsy",
            "timestamp": 1409197740,
            "txt_content": "niop 发表于 2014-8-28 11:41\n你就是新手\n你看他的签名。。。。。"
        },
        {
            "author": "eaaaaa",
            "timestamp": 1409197860,
            "txt_content": "ZGA 发表于 2014-8-28 11:43\nNEI TMI在服务器里如果没有权限 是不可能用的\n            ——你说，我是新手么？ ...\n哦，是吗？只玩单机无力"
        },
        {
            "author": "1134516880",
            "timestamp": 1409197920,
            "txt_content": "挂大把= = 最好你去隐身监视一下"
        },
        {
            "author": "ZGA",
            "timestamp": 1409197980,
            "txt_content": "eaaaaa 发表于 2014-8-28 11:51\n哦，是吗？只玩单机无力\n你也要多玩玩多人啊→_→\n            ——你说，我是新手么？"
        }
    ]
}