{
    "title": "制作能坐的橡木楼梯",
    "author": "ddee",
    "replyCount": 19,
    "timestamp": 1432125360,
    "txt_content": " 本帖最后由 ddee 于 2015-5-22 18:08 编辑 \n\n大家好，我是ddee，今天再次来发帖，这次不是mod，也不是服务器，是我的最新研究成果，不知有没有“煋”。\n这是一个简单而且神奇的楼梯，建筑党们经常用楼梯代替椅子，但是那个楼梯不能坐，所以我来教大家怎么做能坐的椅子（不会把矿车清理的服务器也可以）\n看图：这里\n第一步：如图放置【不多说】\n第二步：如图放置【不多说】\n第三步：如图放置矿车后，推动矿车【记得一定要加速铁轨】\n第四步：将橡木楼梯以外的东西装饰一下【铁轨和红石火把可以拆掉】\n第五步：你就能高高兴兴的去右击楼梯【矿车】坐上去了\nPS. 哪位大神能把矿车隐藏加我QQ：2634653019\n我发现，有人抄袭我，管理员居然没警告，还在主页上有他的连接，太气人了！！！谁要是再火星我就***了你！！！\n",
    "replies": [
        {
            "author": "Ayano舞蝶",
            "timestamp": 1432125480,
            "txt_content": "好麻烦 还要点开啊    不能直接把图上传上来么..."
        },
        {
            "author": "1351680343zxw",
            "timestamp": 1432125900,
            "txt_content": "机智的lz"
        },
        {
            "author": "哈鱼",
            "timestamp": 1432126920,
            "txt_content": "我发表一下我的看法：【不多说】"
        },
        {
            "author": "天渊·启",
            "timestamp": 1432127280,
            "txt_content": "LZ非火星也，致远星人耳······"
        },
        {
            "author": "小白~别喷。",
            "timestamp": 1432127400,
            "txt_content": "我怎么没看到图"
        },
        {
            "author": "20809225",
            "timestamp": 1432127400,
            "txt_content": "额\n早已会了"
        },
        {
            "author": "5749767",
            "timestamp": 1432128600,
            "txt_content": "超出太阳系了已经。。。。。\n不过还是支持一下。"
        },
        {
            "author": "艾淼",
            "timestamp": 1432129020,
            "txt_content": "我从未见过如此厚颜无耻之徒！"
        },
        {
            "author": "繁星满天",
            "timestamp": 1432130820,
            "txt_content": "代替了插件..."
        },
        {
            "author": "时光如年i",
            "timestamp": 1432132080,
            "txt_content": "如图所示.....图呢！还要我去百度打开看，你不能复制链接在贴过来吗？"
        },
        {
            "author": "怨念_无言",
            "timestamp": 1432169400,
            "txt_content": "居然厚颜无耻到这种地步"
        },
        {
            "author": "瓦叫数字菌",
            "timestamp": 1432171500,
            "txt_content": "也算是一种创新咯  毕竟花了心思的"
        },
        {
            "author": "saokedi1",
            "timestamp": 1432175280,
            "txt_content": "hhhhhhhhhh"
        },
        {
            "author": "ybb135788",
            "timestamp": 1432185240,
            "txt_content": "话说手机版也能用吧"
        },
        {
            "author": "840196733mw",
            "timestamp": 1432185660,
            "txt_content": "生存模式隐藏矿车几乎是不可能的，创造用命令方块是100%可以的"
        },
        {
            "author": "18873487788",
            "timestamp": 1432186140,
            "txt_content": "哈鱼 发表于 2015-5-20 21:02\n我发表一下我的看法：【不多说】\n大家好 我是来水经验的 水经验的"
        },
        {
            "author": "ddee",
            "timestamp": 1432289340,
            "txt_content": "ybb135788 发表于 2015-5-21 13:14\n话说手机版也能用吧\n恩，可以"
        },
        {
            "author": "ddee",
            "timestamp": 1432289460,
            "txt_content": "Ayano舞蝶 发表于 2015-5-20 20:38\n好麻烦 还要点开啊    不能直接把图上传上来么...\n图太大了"
        },
        {
            "author": "⭐✔️",
            "timestamp": 1432297260,
            "txt_content": "请善用论坛图片上传功能\n请在三日之内在主题中补全图片，补完了后私信我解除关闭"
        }
    ]
}