{
    "title": "我要做小型RPG地图，求大神告诉我怎么做和命令方块的所有指令",
    "author": "425537974",
    "replyCount": 5,
    "timestamp": 1441263480,
    "txt_content": "求大神啊，告诉我简单的RPG地图怎么做，小弟跪了啊，急需！！！！！其他大神求告诉所有单人可用的命令方块和对话框的指令啊，49金粒不成敬意，小弟以后必当回报！！！！！欢迎大家{:10_494:}[rail_corner1][rail_corner4]        [rail_corner1][rail_corner4] \n                   \n                   [rail_corner2][rail_corner3]",
    "replies": [
        {
            "author": "425537974",
            "timestamp": 1441263540,
            "txt_content": "快快快，每日一顶！！！"
        },
        {
            "author": "火柴盒先森",
            "timestamp": 1441265520,
            "txt_content": "建筑：\nAZ的10分钟高大上系列建筑教程\nhttp://www.mcbbs.net/thread-463435-1-1.html\n命令方块：\n贰逼的索引贴\nhttp://www.mcbbs.net/thread-237123-1-1.html\nPotatoMaster的教程\nhttp://www.mcbbs.net/thread-210012-1-1.html\nTyson的教程\nhttp://www.mcbbs.net/thread-223196-1-1.html\nSoft的Mce滤器大全\nhttp://www.mcbbs.net/thread-234024-1-1.html\n命令方块全图文教程\nhttp://www.mcbbs.net/thread-260804-1-1.html\n1.8.3+45+10个命令基础用法教程\nhttp://www.mcbbs.net/thread-440268-1-1.html\n\n似乎有点多（命令方块是大坑.）"
        },
        {
            "author": ".|°夨.忆ヽ",
            "timestamp": 1441265700,
            "txt_content": "425537974 发表于 2015-9-3 14:59\n快快快，每日一顶！！！\n您好~\nPRG地图教程：http://www.yxdown.com/gonglue/130001.html\n命令方块教程：http://www.mcbbs.net/thread-260804-1-1.html"
        },
        {
            "author": "ylzim",
            "timestamp": 1441335960,
            "txt_content": "http://www.mcbbs.net/thread-432888-1-1.html【地图制作福音】更改地图名称颜色与字体，另附更改作弊    是地图颜色更改  令人赏心悦目\n\nhttp://www.mcbbs.net/thread-492096-1-1.html  计分板的问题  加入死亡次数 增加地图的新意\n\n我的世界命令方块指令http://zhidao.baidu.com/link?url ... WfYmIzW-QQtkRbn5yh7   这个可以帮助楼主做RPG所需的指令\n\nhttp://www.mcbbs.net/thread-440268-1-1.html 同上\n\nhttp://www.mcbbs.net/thread-78479-1-1.html NBT  RPG必备！！！！！！\n\n望楼主采纳！"
        },
        {
            "author": "topjxr",
            "timestamp": 1442283600,
            "txt_content": "一般rpg用到的是/say和/tp"
        }
    ]
}