{
    "title": "中秋节快乐",
    "author": "猪一头",
    "replyCount": 5,
    "timestamp": 1443313080,
    "txt_content": "今天我小学同学给我私聊发了一个中秋节快乐\n真是感动地不要不要的\n大家都怎么过中秋节嘞",
    "replies": [
        {
            "author": "cheesewoo",
            "timestamp": 1443313800,
            "txt_content": "中秋快乐!!!"
        },
        {
            "author": "snowclay",
            "timestamp": 1443313980,
            "txt_content": "。。。没啥感觉该干啥干啥。。"
        },
        {
            "author": "PETER·篠",
            "timestamp": 1443319860,
            "txt_content": "中秋快乐~~"
        },
        {
            "author": "影子o0",
            "timestamp": 1443320700,
            "txt_content": "中秋快乐"
        },
        {
            "author": "zy367359",
            "timestamp": 1443323280,
            "txt_content": "同乐 同乐 同乐 重要的事情说3遍{:10_492:}"
        }
    ]
}