{
    "title": "[安全]NoXray——反作弊[sponge插件][1.10.2]",
    "author": "优妹酱",
    "replyCount": 12,
    "timestamp": 1474085580,
    "txt_content": " 本帖最后由 优妹酱 于 2017-4-24 07:40 编辑 \n介绍\n作者原话\nNoXray是一个可以在SpongeVanilla和SpongeForge工作的混合（mixin）插件。多亏混合（mixin）我才得以做出一个有效并且延时低的系统。它的工作原理是通过玩家打破一个方块，修改方块在发送时间和更新周围方块的机制。 请注意，矿洞是可见的，因为他们在空气方块旁边，但这足以让熊孩子慢下来，对付Xray十分有效。\n\n\n食用方法\n把插件丢进服务端mods然后重启就可以啦（海绵端的插件就是丢mods的休想水帖）\n\n虾仔地址\n上方有下载地址\n什么？尼说进不去？真是拿你没办法呢……\n\n\n\nNoXray.jar\n(32.32 KB, 下载次数: 190)\n\n\n\n2017-4-24 07:40 上传\n点击文件名下载附件\n才不是为了你呢，哼！\n\n\n\n\n\n\n\n\n\n\n\nd0431a504e8a70a9d6d754d2a88b53849cac6eb5_1_690x193.png (257.16 KB, 下载次数: 1)\n\n下载附件\n\n2016-9-17 12:09 上传\n\n\n\n\n\n\n另外要说的话因为是搬完才发现跟酷手大大重搬，也已经跟他本人说过了。酷手大大可比我勤奋的多，要是我更新的晚的话大家可以去酷手大大那里下载\n来自群组: InfinityStudio\n",
    "replies": [
        {
            "author": "Oscar_W",
            "timestamp": 1474090080,
            "txt_content": "会卡服么"
        },
        {
            "author": "优妹酱",
            "timestamp": 1474091280,
            "txt_content": "oscarab 发表于 2016-9-17 13:28\n会卡服么\n不会太卡，因为不像假矿插件做伪装矿会占用大量内存，这个只是改变了一些机制达到透视看不到矿。"
        },
        {
            "author": "AD【钙奶】",
            "timestamp": 1475234340,
            "txt_content": "1.7.10可以使用吗？"
        },
        {
            "author": "zhaoyitao011",
            "timestamp": 1475499360,
            "txt_content": "1.7.10 没生成配置文件"
        },
        {
            "author": "annie540",
            "timestamp": 1475713500,
            "txt_content": "剑灵的小伙伴（滑稽）"
        },
        {
            "author": "qwe459223217",
            "timestamp": 1487506440,
            "txt_content": "已经下载 加入收藏 谢谢楼主"
        },
        {
            "author": "qwe459223217",
            "timestamp": 1487507400,
            "txt_content": "希望出更多的版本"
        },
        {
            "author": "2827650172",
            "timestamp": 1487755200,
            "txt_content": "很不错，顶楼主！继续加油"
        },
        {
            "author": "HB123X",
            "timestamp": 1487833560,
            "txt_content": "在意不怕熊孩子的xray了"
        },
        {
            "author": "狂拽天下",
            "timestamp": 1487844480,
            "txt_content": "犹如玉带明珠"
        },
        {
            "author": "zh528018659",
            "timestamp": 1534578360,
            "txt_content": "提示: 作者被禁止或删除 内容自动屏蔽"
        },
        {
            "author": "Q1532943507",
            "timestamp": 1534583100,
            "txt_content": "不错，挺好用啊"
        }
    ]
}