{
    "title": "我的皮肤真的很奇葩？",
    "author": "sayway123",
    "replyCount": 48,
    "timestamp": 1361081700,
    "txt_content": " 本帖最后由 sayway123 于 2013-2-17 14:33 编辑 \n\n如题\n我的皮肤真的很奇葩吗？{:10_535:}\n个人认为很霸气\n你们觉得呢？\n\n\n\n\n2013-02-16_15.37.39.png (222.84 KB, 下载次数: 0)\n\n下载附件\n\n2013-2-17 14:14 上传\n\n\n\n\n\n再看我的头像？\n",
    "replies": [
        {
            "author": "Aikawastep",
            "timestamp": 1361081760,
            "txt_content": "不文明！拉去毙了！"
        },
        {
            "author": "雨落残阳",
            "timestamp": 1361081820,
            "txt_content": "啊啊、雨落好羞涩nia~完全不敢直视nia~"
        },
        {
            "author": "毒蛇",
            "timestamp": 1361081820,
            "txt_content": "Aikawastep 发表于 2013-2-17 14:16 \n不文明！拉去毙了！\n还是加上衣服吧，否则枪毙"
        },
        {
            "author": "sayway123",
            "timestamp": 1361081880,
            "txt_content": "雨落残阳 发表于 2013-2-17 14:17 \n啊啊、雨落好羞涩nia~完全不敢直视nia~\n我勒个去\n真的这样吗\n我震惊了"
        },
        {
            "author": "Aikawastep",
            "timestamp": 1361081880,
            "txt_content": "毒蛇 发表于 2013-2-17 14:17 \n还是加上衣服吧，否则枪毙\n你回复我干嘛=-="
        },
        {
            "author": "1095486321",
            "timestamp": 1361082000,
            "txt_content": "提示: 作者被禁止或删除 内容自动屏蔽"
        },
        {
            "author": "919begin",
            "timestamp": 1361082000,
            "txt_content": "刚搞完基的皮肤吗"
        },
        {
            "author": "tt5669453",
            "timestamp": 1361082240,
            "txt_content": "拉出去拿AK毙了,楼下跟随队形"
        },
        {
            "author": "sayway123",
            "timestamp": 1361082360,
            "txt_content": "这。。。\n不要这样。。。"
        },
        {
            "author": "784746813",
            "timestamp": 1361082360,
            "txt_content": "好像菜鸟视频的皮肤"
        },
        {
            "author": "Fcy_lity",
            "timestamp": 1361082420,
            "txt_content": "表示要在旁边拉个妹纸"
        },
        {
            "author": "sayway123",
            "timestamp": 1361082420,
            "txt_content": "好吧。。。                                  \n\n\n"
        },
        {
            "author": "784746813",
            "timestamp": 1361082420,
            "txt_content": "也不怎么像。。。。"
        },
        {
            "author": "784746813",
            "timestamp": 1361082480,
            "txt_content": "784746813 发表于 2013-2-17 14:27 \n也不怎么像。。。。\n菜鸟视频是全裸的。。。然后又有裤子了"
        },
        {
            "author": "sayway123",
            "timestamp": 1361082540,
            "txt_content": "784746813 发表于 2013-2-17 14:28 \n菜鸟视频是全裸的。。。然后又有裤子了\n看来有不同啊。。。           "
        },
        {
            "author": "mclauncher",
            "timestamp": 1361082720,
            "txt_content": "这个，没什么。。。。。。"
        },
        {
            "author": "无痕",
            "timestamp": 1361082780,
            "txt_content": "惊险亚当？！"
        },
        {
            "author": "sayway123",
            "timestamp": 1361082780,
            "txt_content": "无痕 发表于 2013-2-17 14:33 \n惊险亚当？！\n还差个夏娃呢我还      "
        },
        {
            "author": "xkpdy",
            "timestamp": 1361082960,
            "txt_content": "{:10_499:}狗眼瞎了汪~！！"
        },
        {
            "author": "z736027620",
            "timestamp": 1361083080,
            "txt_content": "784746813 发表于 2013-2-17 14:26 \n好像菜鸟视频的皮肤\n不是=--菜鸟的是少年=-="
        },
        {
            "author": "784746813",
            "timestamp": 1361083140,
            "txt_content": "z736027620 发表于 2013-2-17 14:38 \n不是=--菜鸟的是少年=-=\n美国那个视频，也叫菜鸟！搞笑得很呐！"
        },
        {
            "author": "MC陈",
            "timestamp": 1361083140,
            "txt_content": "孩子碉堡了"
        },
        {
            "author": "z736027620",
            "timestamp": 1361083140,
            "txt_content": "784746813 发表于 2013-2-17 14:39 \n美国那个视频，也叫菜鸟！搞笑得很呐！\n我知道=-= 菜鸟来了"
        },
        {
            "author": "Оil",
            "timestamp": 1361083200,
            "txt_content": "甲：“看到了没有！就是那幢房子的阳台上，A目标就在那里！”\nOil：“呼叫鸡窝，是否击毙目标？完毕。”\n乙：“回复母鸡：尽量活捉目标，但如果目标率先发动对小队有威胁性的攻击，允许击毙目标。”\nOil：“了解。全体队员以隐蔽状态向A目标行进！”\n小队成员（甲、丙、丁、戊）：“明白！”"
        },
        {
            "author": "784746813",
            "timestamp": 1361083200,
            "txt_content": "z736027620 发表于 2013-2-17 14:39 \n我知道=-= 菜鸟来了\n是的。。。。。"
        },
        {
            "author": "1412942842",
            "timestamp": 1361084040,
            "txt_content": "风吹蛋蛋凉{:10_535:}"
        },
        {
            "author": "458529276",
            "timestamp": 1361085960,
            "txt_content": "一点也不霸气{:10_535:}\n我的是全luo的{:10_547:}"
        },
        {
            "author": "xieshuxuan",
            "timestamp": 1361087100,
            "txt_content": "我的全裸。。打上了马赛克。。"
        },
        {
            "author": "ugattiveyron",
            "timestamp": 1361087100,
            "txt_content": "这不是野人吗，真么跑这来了"
        },
        {
            "author": "sayway123",
            "timestamp": 1361088180,
            "txt_content": "xieshuxuan 发表于 2013-2-17 15:45 \n我的全裸。。打上了马赛克。。\n你们这些变态\n要有限度啊"
        },
        {
            "author": "shentong",
            "timestamp": 1361088300,
            "txt_content": "拉出去给我毙了"
        },
        {
            "author": "oWee",
            "timestamp": 1361089200,
            "txt_content": "其实我只是好奇手臂上的那两个黑点"
        },
        {
            "author": "伯伯大哥",
            "timestamp": 1361089740,
            "txt_content": " 本帖最后由 伯伯大哥 于 2013-2-17 16:30 编辑 \n\n叶子去掉吧   这样更霸气！\n[fly]别看我 路过的字幕军[/fly]"
        },
        {
            "author": "moonbiow",
            "timestamp": 1361093280,
            "txt_content": "第一眼看到皮肤 确实有伤大雅，感觉不能忍啊\n第二眼看到楼主头像...好吧，皮肤什么的我忍了"
        },
        {
            "author": "1159141564",
            "timestamp": 1361094840,
            "txt_content": "不文明！拉去毙了"
        },
        {
            "author": "yxyhcc",
            "timestamp": 1361095140,
            "txt_content": "我爱这皮肤{:10_520:}"
        },
        {
            "author": "ever-lose",
            "timestamp": 1361095260,
            "txt_content": "猥琐"
        },
        {
            "author": "1457666076",
            "timestamp": 1361095500,
            "txt_content": "赶紧穿衣服小心被枪毙"
        },
        {
            "author": "强子、",
            "timestamp": 1361097060,
            "txt_content": "亚当而已,很常见"
        },
        {
            "author": "聽、天邊之音",
            "timestamp": 1361097360,
            "txt_content": "绳子捆起来~蜡烛点起来~皮鞭挥起来~"
        },
        {
            "author": "7715566",
            "timestamp": 1361097600,
            "txt_content": "啊~~~~楼主好色色，快穿上衣服"
        },
        {
            "author": "ppkk998",
            "timestamp": 1361098200,
            "txt_content": "LZ是野人拉去枪毙~！"
        },
        {
            "author": "aka01",
            "timestamp": 1361101620,
            "txt_content": "还好AvA。。"
        },
        {
            "author": "sayway123",
            "timestamp": 1361101740,
            "txt_content": "moonbiow 发表于 2013-2-17 17:28第一眼看到皮肤 确实有伤大雅，感觉不能忍啊 第二眼看到楼主头像...好吧，皮肤什么的我忍了\n诶诶\n原来我的头像杀伤力如此强大"
        },
        {
            "author": "sayway123",
            "timestamp": 1361102100,
            "txt_content": "伯伯大哥 发表于 2013-2-17 16:29叶子去掉吧   这样更霸气！ [fly]别看我 路过的字幕军[/fly]\n叶子去掉就不是霸气了\n是流氓"
        },
        {
            "author": "sayway123",
            "timestamp": 1361102100,
            "txt_content": "伯伯大哥 发表于 2013-2-17 16:29叶子去掉吧   这样更霸气！ [fly]别看我 路过的字幕军[/fly]\n叶子去掉就不是霸气了\n是流氓"
        },
        {
            "author": "sayway123",
            "timestamp": 1361102280,
            "txt_content": "伯伯大哥 发表于 2013-2-17 16:29叶子去掉吧   这样更霸气！ [fly]别看我 路过的字幕军[/fly]\n叶子去掉就不是霸气了\n是流氓"
        },
        {
            "author": "sayway123",
            "timestamp": 1361103060,
            "txt_content": "毒蛇 发表于 2013-2-17 14:17还是加上衣服吧，否则枪毙\n兄弟你安错键了      "
        }
    ]
}