{
    "title": "新手上路，在此报道。",
    "author": "十三张唱片",
    "replyCount": 10,
    "timestamp": 1569675540,
    "txt_content": "新手上路，还请各位多多关照。",
    "replies": [
        {
            "author": "Chickenball",
            "timestamp": 1569675600,
            "txt_content": "你好!我也是刚玩不久的。你现在还加不了好友，我们先交个朋友吧QAQ"
        },
        {
            "author": "坑触可",
            "timestamp": 1569678000,
            "txt_content": "欢迎新人。"
        },
        {
            "author": "文豪小绝",
            "timestamp": 1569680100,
            "txt_content": "欢迎新人，这里是咕咕咕小绝"
        },
        {
            "author": "18368060842",
            "timestamp": 1569685680,
            "txt_content": "新人你好 注意多看看版规"
        },
        {
            "author": "mj0v0",
            "timestamp": 1569737220,
            "txt_content": "欢迎新人"
        },
        {
            "author": "cvcocvc",
            "timestamp": 1569738540,
            "txt_content": "等级低不一定就是新手"
        },
        {
            "author": "小锤子yo",
            "timestamp": 1569738900,
            "txt_content": "欢迎新人"
        },
        {
            "author": "kuangshijs",
            "timestamp": 1569740820,
            "txt_content": "欢迎新人"
        },
        {
            "author": "萌主丁白海",
            "timestamp": 1569742680,
            "txt_content": "欢迎欢迎 awa"
        },
        {
            "author": "YG丶殇羽",
            "timestamp": 1569747060,
            "txt_content": "我也是新人哈哈"
        }
    ]
}