{
    "title": "[tc6]神秘时代6的杂项讨论",
    "author": "iceer",
    "replyCount": 6,
    "timestamp": 1571621220,
    "txt_content": "神秘5我记得有3种祭坛来着，奥术注魔祭坛，邪术注魔祭坛，荒古注魔祭坛（没玩过tc5）。tc6不知道还有没有了。\n神秘6要怎么样才可以去外域啊~\n神秘6连奥法缰绳貌似都没有了。\n有没有人知道神秘6的核心是怎么回事啊",
    "replies": [
        {
            "author": "吃东西的猫",
            "timestamp": 1571625900,
            "txt_content": "我只玩过神秘4，神秘5.6，还没有玩= ="
        },
        {
            "author": "愿爱无界",
            "timestamp": 1571847900,
            "txt_content": "我只玩神秘4"
        },
        {
            "author": "iceer",
            "timestamp": 1571887620,
            "txt_content": "我神秘4玩的特别熟。最近才入坑神秘6.觉得focus系统变得更加强大了"
        },
        {
            "author": "431306504",
            "timestamp": 1571990640,
            "txt_content": "停滞于神秘4，难以向前"
        },
        {
            "author": "iceer",
            "timestamp": 1571999880,
            "txt_content": "你可以试试tc6，也挺好玩的，但是貌似外域没有做了"
        },
        {
            "author": "心空NaLa",
            "timestamp": 1572002820,
            "txt_content": "我玩过神秘6，但是不玩了之后就忘了。。\n"
        }
    ]
}