{
    "title": "port mapper报错，求大佬帮忙",
    "author": "2356820887",
    "replyCount": 2,
    "timestamp": 1580091660,
    "txt_content": "本人萌新一枚，求dalao解释越详细越好\n\n\n\n\n\nAV]OT0N}ZVQ1SORR(F(7WUY.png\n(21.43 KB, 下载次数: 0)\n\n\n\n\n下载附件\n\n\n2020-1-27 10:20 上传\n\n\n\n\n\n\n\n\n不管改什么都会报错\n\n\n\n\n\n\n",
    "replies": [
        {
            "author": "xmdhs",
            "timestamp": 1580091660,
            "txt_content": "端口映射的软件吗，建议换别的"
        },
        {
            "author": "cc7w",
            "timestamp": 1580129100,
            "txt_content": "请尝试换用\n推荐 Sakura Frp：\nhttps://www.natfrp.com/ （官网）\nhttps://www.mcbbs.net/thread-831469-1-1.html （教程贴）\n\n有帮助请您在本回复右下角点击设置最佳答案。\n您的认可是对回答者最大的支持！"
        }
    ]
}